{
	"name": "deletedata",
	"properties": {
		"activities": [
			{
				"name": "Delete1",
				"type": "Delete",
				"dependsOn": [],
				"policy": {
					"timeout": "0.12:00:00",
					"retry": 0,
					"retryIntervalInSeconds": 30,
					"secureOutput": false,
					"secureInput": false
				},
				"userProperties": [],
				"typeProperties": {
					"dataset": {
						"referenceName": "DS_ABS_CopyAllFiles_kabirahuja0103_retaildb_customerscsv",
						"type": "DatasetReference"
					},
					"logStorageSettings": {
						"linkedServiceName": {
							"referenceName": "LS_AzureBlobStorage_kabirahuja0103",
							"type": "LinkedServiceReference"
						},
						"path": "retaildb"
					},
					"enableLogging": true,
					"storeSettings": {
						"type": "AzureBlobStorageReadSettings",
						"recursive": true,
						"wildcardFileName": "*",
						"enablePartitionDiscovery": false
					}
				}
			}
		],
		"folder": {
			"name": "GetMetadata"
		},
		"annotations": []
	}
}